psps/__init__.py
psps/simulate_helpers.py
psps/simulate_transit.py
psps/transit_class.py
psps/utils.py
psps-0.0.9.dist-info/LICENSE
psps-0.0.9.dist-info/METADATA
psps-0.0.9.dist-info/WHEEL
psps-0.0.9.dist-info/top_level.txt
psps-0.0.9.dist-info/RECORD
