Metadata-Version: 2.1
Name: psps
Version: 0.0.9
Summary: planetary system population synthesis
Author: Chris Lam
Author-email: Christopher Lam <c.lam@ufl.edu>
License: MIT License
Project-URL: Homepage, https://github.com/cl3425/psps
Project-URL: Bug Tracker, https://github.com/cl3425/psps/issues
Classifier: Programming Language :: Python :: 3
Classifier: License :: OSI Approved :: MIT License
Classifier: Operating System :: OS Independent
Requires-Python: >=3.7
License-File: LICENSE
